{
  "sharpness": 1.7383324192320755,
  "gradient_smoothness": 0.22298353190998424,
  "loss_mean": 0.0,
  "loss_std": 0.0,
  "loss_trend": -1.2616417314458965e-09,
  "parameter_norm": 29.86162389298232,
  "lambda_max_10": -77.70530700683594,
  "hessian_trace_10": 738.6133331298828,
  "fim_trace": 9103.85383450985,
  "step_count": 10,
  "timestamp": 1764177062.1766562,
  "episode_reward": 1119.432373046875,
  "num_steps": 360448,
  "feature_compute_time_s": 8.529751062393188,
  "train_iter_time_s": 4.410017728805542,
  "init_seed": 200,
  "train_seed": 202,
  "best_reward_so_far": -Infinity
}