{
  "sharpness": 1.481671238053838,
  "gradient_smoothness": 0.6292909900711906,
  "loss_mean": 0.0,
  "loss_std": 0.0,
  "loss_trend": 5.523462853391535e-10,
  "parameter_norm": 101.7685702942181,
  "lambda_max_10": -5.840513706207275,
  "hessian_trace_10": -40.807709503173825,
  "fim_trace": 1739.7664666473866,
  "step_count": 14,
  "timestamp": 1764177662.570812,
  "episode_reward": -319.7618713378906,
  "num_steps": 491520,
  "feature_compute_time_s": 4.839813470840454,
  "train_iter_time_s": 2.7760353088378906,
  "init_seed": 200,
  "train_seed": 200,
  "best_reward_so_far": -Infinity
}