{
  "sharpness": 1.6803368676585881,
  "gradient_smoothness": 0.15473298580393569,
  "loss_mean": 0.0,
  "loss_std": 0.0,
  "loss_trend": 7.3948957988586025e-09,
  "parameter_norm": 30.80720563979671,
  "lambda_max_10": -36.26632308959961,
  "hessian_trace_10": 293.10450592041013,
  "fim_trace": 5687.7516659498215,
  "step_count": 3,
  "timestamp": 1764177102.722144,
  "episode_reward": 1353.0372314453125,
  "num_steps": 131072,
  "feature_compute_time_s": 5.101441860198975,
  "train_iter_time_s": 2.882695436477661,
  "init_seed": 200,
  "train_seed": 200,
  "best_reward_so_far": -Infinity
}