{
  "sharpness": 1.7881041878983626,
  "gradient_smoothness": 0.16383542073840707,
  "loss_mean": 0.0,
  "loss_std": 0.0,
  "loss_trend": 4.155195507729197e-09,
  "parameter_norm": 29.1064473702455,
  "lambda_max_10": 44.632659912109375,
  "hessian_trace_10": 212.28137893676757,
  "fim_trace": 2942.3043117821217,
  "step_count": 3,
  "timestamp": 1764168256.3841155,
  "episode_reward": 1504.02001953125,
  "num_steps": 131072,
  "feature_compute_time_s": 6.807365894317627,
  "train_iter_time_s": 3.990898847579956,
  "init_seed": 203,
  "train_seed": 200,
  "best_reward_so_far": -Infinity
}