{
  "sharpness": 1.781173293152391,
  "gradient_smoothness": 0.17101525287049896,
  "loss_mean": 0.0,
  "loss_std": 0.0,
  "loss_trend": 2.3476403372484795e-09,
  "parameter_norm": 29.587404253947543,
  "lambda_max_10": -31.923683166503906,
  "hessian_trace_10": 278.29881286621094,
  "fim_trace": 2886.7231818139553,
  "step_count": 6,
  "timestamp": 1764153183.742594,
  "episode_reward": 3260.13037109375,
  "num_steps": 229376,
  "feature_compute_time_s": 5.109960079193115,
  "train_iter_time_s": 5.582856893539429,
  "init_seed": 200,
  "train_seed": 207,
  "best_reward_so_far": -Infinity
}