{
  "sharpness": 1.7104316337691436,
  "gradient_smoothness": 0.12331404491839322,
  "loss_mean": 0.0,
  "loss_std": 0.0,
  "loss_trend": 1.1823516016134998e-09,
  "parameter_norm": 29.263353330029943,
  "lambda_max_10": -1.8855730295181274,
  "hessian_trace_10": 206.34430427551268,
  "fim_trace": 4790.1175464093685,
  "step_count": 6,
  "timestamp": 1764167049.7712748,
  "episode_reward": 1665.2244873046875,
  "num_steps": 229376,
  "feature_compute_time_s": 7.215620040893555,
  "train_iter_time_s": 3.3085508346557617,
  "init_seed": 200,
  "train_seed": 201,
  "best_reward_so_far": -Infinity
}