{
  "sharpness": 2.4361490085275954,
  "gradient_smoothness": 0.15815985912179625,
  "loss_mean": 0.0,
  "loss_std": 0.0,
  "loss_trend": 5.553865354548159e-10,
  "parameter_norm": 29.970044686193322,
  "lambda_max_10": -29.79336929321289,
  "hessian_trace_10": 205.51539764404296,
  "fim_trace": 1741.7654730677605,
  "step_count": 7,
  "timestamp": 1764167619.3397899,
  "episode_reward": 1273.1588134765625,
  "num_steps": 262144,
  "feature_compute_time_s": 6.628767013549805,
  "train_iter_time_s": 4.293058395385742,
  "init_seed": 201,
  "train_seed": 200,
  "best_reward_so_far": -Infinity
}