{
  "sharpness": 3.1264966412559687,
  "gradient_smoothness": 0.10764865845640466,
  "loss_mean": 0.0,
  "loss_std": 0.0,
  "loss_trend": 2.9802224084089725e-10,
  "parameter_norm": 30.525136722073096,
  "lambda_max_10": -40.8988037109375,
  "hessian_trace_10": 374.25565643310546,
  "fim_trace": 2452.7038339674473,
  "step_count": 7,
  "timestamp": 1764177148.0285783,
  "episode_reward": 931.6522827148438,
  "num_steps": 262144,
  "feature_compute_time_s": 5.562561511993408,
  "train_iter_time_s": 2.764221668243408,
  "init_seed": 201,
  "train_seed": 200,
  "best_reward_so_far": -Infinity
}