{
  "sharpness": 2.2411295031666234,
  "gradient_smoothness": 0.14026473613176507,
  "loss_mean": 0.0,
  "loss_std": 0.0,
  "loss_trend": 5.640464444923243e-10,
  "parameter_norm": 31.21253341402894,
  "lambda_max_10": -37.98765563964844,
  "hessian_trace_10": 143.81887550354003,
  "fim_trace": 6603.438462257385,
  "step_count": 4,
  "timestamp": 1764170284.9887495,
  "episode_reward": 1462.919677734375,
  "num_steps": 163840,
  "feature_compute_time_s": 5.030351638793945,
  "train_iter_time_s": 3.4970033168792725,
  "init_seed": 200,
  "train_seed": 201,
  "best_reward_so_far": -Infinity
}