{
  "sharpness": 1.5069659455892639,
  "gradient_smoothness": 0.14743921720641137,
  "loss_mean": 0.0,
  "loss_std": 0.0,
  "loss_trend": -5.288092517738723e-09,
  "parameter_norm": 29.84319255840648,
  "lambda_max_10": -25.350990295410156,
  "hessian_trace_10": 369.04925537109375,
  "fim_trace": 3899.0108845457435,
  "step_count": 5,
  "timestamp": 1764152127.7867417,
  "episode_reward": 1357.8536376953125,
  "num_steps": 196608,
  "feature_compute_time_s": 9.383275270462036,
  "train_iter_time_s": 3.596771001815796,
  "init_seed": 200,
  "train_seed": 206,
  "best_reward_so_far": -Infinity
}