{
  "sharpness": 1.824493582786274,
  "gradient_smoothness": 0.19212287462270314,
  "loss_mean": 0.0,
  "loss_std": 0.0,
  "loss_trend": -2.631961775838567e-08,
  "parameter_norm": 29.201319884478586,
  "lambda_max_10": 39.99413299560547,
  "hessian_trace_10": 282.9658401489258,
  "fim_trace": 4562.310974478722,
  "step_count": 2,
  "timestamp": 1764166798.1136525,
  "episode_reward": 1338.688232421875,
  "num_steps": 98304,
  "feature_compute_time_s": 4.9666361808776855,
  "train_iter_time_s": 3.3326334953308105,
  "init_seed": 200,
  "train_seed": 201,
  "best_reward_so_far": -Infinity
}