{
  "sharpness": 1.8141077735900393,
  "gradient_smoothness": 0.19259110540242846,
  "loss_mean": 0.0,
  "loss_std": 0.0,
  "loss_trend": -3.1278615550190264e-09,
  "parameter_norm": 30.04871556855146,
  "lambda_max_10": 54.464473724365234,
  "hessian_trace_10": 242.03846435546876,
  "fim_trace": 4482.765890024602,
  "step_count": 8,
  "timestamp": 1764178260.7256985,
  "episode_reward": 1369.8173828125,
  "num_steps": 294912,
  "feature_compute_time_s": 5.9069201946258545,
  "train_iter_time_s": 3.083385467529297,
  "init_seed": 207,
  "train_seed": 200,
  "best_reward_so_far": -Infinity
}