{
  "sharpness": 7.6701246510843255,
  "gradient_smoothness": 0.35111010292641115,
  "loss_mean": 0.0,
  "loss_std": 0.0,
  "loss_trend": -7.125087016662938e-10,
  "parameter_norm": 101.81062923151602,
  "lambda_max_10": -2046.893310546875,
  "hessian_trace_10": 3685.478375244141,
  "fim_trace": 21663370.437562943,
  "step_count": 12,
  "timestamp": 1764170487.4485068,
  "episode_reward": -592.5516967773438,
  "num_steps": 425984,
  "feature_compute_time_s": 5.385845184326172,
  "train_iter_time_s": 2.682922601699829,
  "init_seed": 200,
  "train_seed": 203,
  "best_reward_so_far": -Infinity
}