{
  "sharpness": 1.6637355620472005,
  "gradient_smoothness": 0.0,
  "parameter_norm": 29.1431233307606,
  "lambda_max_10": 13.207778930664062,
  "hessian_trace_10": 191.64188079833986,
  "fim_trace": 1179.8011015355587,
  "step_count": 0,
  "timestamp": 1764160053.7280104,
  "episode_reward": 1432.834716796875,
  "num_steps": 32768,
  "feature_compute_time_s": 5.093857049942017,
  "train_iter_time_s": 4.477013111114502,
  "init_seed": 206,
  "train_seed": 200,
  "best_reward_so_far": -Infinity
}