{
  "sharpness": 1.7737083370800082,
  "gradient_smoothness": 0.1324240835044462,
  "loss_mean": 0.0,
  "loss_std": 0.0,
  "loss_trend": -2.93313038181499e-09,
  "parameter_norm": 29.859103968926558,
  "lambda_max_10": -95.08012390136719,
  "hessian_trace_10": 835.7498291015625,
  "fim_trace": 8916.123785942793,
  "step_count": 4,
  "timestamp": 1764166603.9408417,
  "episode_reward": 1444.121337890625,
  "num_steps": 163840,
  "feature_compute_time_s": 6.099600791931152,
  "train_iter_time_s": 4.877668380737305,
  "init_seed": 200,
  "train_seed": 205,
  "best_reward_so_far": -Infinity
}