{
  "sharpness": 1.8461587070305248,
  "gradient_smoothness": 0.600802617795861,
  "loss_mean": 0.0,
  "loss_std": 0.0,
  "loss_trend": 1.3008858736065166e-10,
  "parameter_norm": 29.24631050939883,
  "lambda_max_10": 41.937217712402344,
  "hessian_trace_10": 232.46722488403321,
  "fim_trace": 3553.942539460957,
  "step_count": 14,
  "timestamp": 1764168185.29074,
  "episode_reward": 1588.0618896484375,
  "num_steps": 491520,
  "feature_compute_time_s": 5.010871887207031,
  "train_iter_time_s": 3.523512363433838,
  "init_seed": 203,
  "train_seed": 200,
  "best_reward_so_far": -Infinity
}