{
  "sharpness": 1.2450027328326807,
  "gradient_smoothness": 0.0,
  "loss_mean": 0.0,
  "loss_std": 0.0,
  "loss_trend": 0.0,
  "parameter_norm": 34.5185678733555,
  "lambda_max_10": -27.471227645874023,
  "hessian_trace_10": 574.3628570556641,
  "fim_trace": 3372.8782638013363,
  "step_count": 1,
  "timestamp": 1765469626.3856823,
  "episode_reward": -9.816577911376953,
  "num_steps": 65536,
  "feature_compute_time_s": 5.7985520362854,
  "train_iter_time_s": 4.01983118057251,
  "init_seed": 205,
  "train_seed": 200,
  "best_reward_so_far": 22.99418476517249
}