{
  "sharpness": 1.5599713059382345,
  "gradient_smoothness": 0.1124645321361484,
  "loss_mean": 0.0,
  "loss_std": 0.0,
  "loss_trend": -1.7963138694823171e-09,
  "parameter_norm": 29.72113858342852,
  "lambda_max_10": 24.357818603515625,
  "hessian_trace_10": 298.42400512695315,
  "fim_trace": 3842.2954391241074,
  "step_count": 9,
  "timestamp": 1764149019.5918746,
  "episode_reward": 1626.57666015625,
  "num_steps": 327680,
  "feature_compute_time_s": 8.042004108428955,
  "train_iter_time_s": 4.132298231124878,
  "init_seed": 200,
  "train_seed": 203,
  "best_reward_so_far": -Infinity
}