{
  "sharpness": 1.7612557706047154,
  "gradient_smoothness": 0.3293023018338604,
  "loss_mean": 0.0,
  "loss_std": 0.0,
  "loss_trend": -6.521627777587822e-11,
  "parameter_norm": 29.76186001674569,
  "lambda_max_10": -36.07426452636719,
  "hessian_trace_10": 223.1017639160156,
  "fim_trace": 3395.5175839960575,
  "step_count": 12,
  "timestamp": 1764148841.1544073,
  "episode_reward": 1460.8223876953125,
  "num_steps": 425984,
  "feature_compute_time_s": 7.248891115188599,
  "train_iter_time_s": 4.996448278427124,
  "init_seed": 200,
  "train_seed": 203,
  "best_reward_so_far": -Infinity
}