{
  "sharpness": 3.5475740181886795,
  "gradient_smoothness": 0.0,
  "parameter_norm": 43.54167685850299,
  "lambda_max_10": -60.926551818847656,
  "hessian_trace_10": 388.7222503662109,
  "fim_trace": 19821.349629998207,
  "step_count": 0,
  "timestamp": 1764178199.467965,
  "episode_reward": 686.837646484375,
  "num_steps": 32768,
  "feature_compute_time_s": 5.199380397796631,
  "train_iter_time_s": 3.8727047443389893,
  "init_seed": 206,
  "train_seed": 200,
  "best_reward_so_far": -Infinity
}